morenines/__init__.py
morenines/__main__.py
morenines/application.py
morenines/exceptions.py
morenines/ignores.py
morenines/index.py
morenines/output.py
morenines/repository.py
morenines/util.py
morenines-1.1.0.dist-info/DESCRIPTION.rst
morenines-1.1.0.dist-info/METADATA
morenines-1.1.0.dist-info/RECORD
morenines-1.1.0.dist-info/WHEEL
morenines-1.1.0.dist-info/entry_points.txt
morenines-1.1.0.dist-info/metadata.json
morenines-1.1.0.dist-info/top_level.txt
